textfission/__init__.py
textfission/cli.py
textfission/core/base.py
textfission/core/cache.py
textfission/core/config.py
textfission/core/exceptions.py
textfission/core/logger.py
textfission/exporters/base.py
textfission/models/base.py
textfission/models/ernie.py
textfission/models/factory.py
textfission/models/openai.py
textfission/models/qianwen.py
textfission/processors/answer_generator.py
textfission/processors/question_generator.py
textfission/processors/text_splitter.py
textfission-0.1.1.dist-info/licenses/LICENSE
textfission-0.1.1.dist-info/METADATA
textfission-0.1.1.dist-info/WHEEL
textfission-0.1.1.dist-info/entry_points.txt
textfission-0.1.1.dist-info/top_level.txt
textfission-0.1.1.dist-info/RECORD
