Metadata-Version: 2.4
Name: textfission
Version: 0.1.1
Summary: A powerful Python library for intelligent text processing, question generation, and answer generation for LLM fine-tuning datasets
Author-email: Sun Zhihan <sunzhihan20@mails.ucas.edu.cn>
Maintainer-email: Sun Zhihan <sunzhihan20@mails.ucas.edu.cn>
License-Expression: MIT
Project-URL: Homepage, https://github.com/GeoSzh/text-fission
Project-URL: Documentation, https://github.com/GeoSzh/text-fission#readme
Project-URL: Repository, https://github.com/GeoSzh/text-fission
Project-URL: Bug Tracker, https://github.com/GeoSzh/text-fission/issues
Keywords: nlp,text-processing,question-generation,llm,fine-tuning,dataset,ai,machine-learning
Classifier: Development Status :: 4 - Beta
Classifier: Intended Audience :: Developers
Classifier: Intended Audience :: Science/Research
Classifier: Operating System :: OS Independent
Classifier: Programming Language :: Python :: 3
Classifier: Programming Language :: Python :: 3.8
Classifier: Programming Language :: Python :: 3.9
Classifier: Programming Language :: Python :: 3.10
Classifier: Programming Language :: Python :: 3.11
Classifier: Programming Language :: Python :: 3.12
Classifier: Topic :: Scientific/Engineering :: Artificial Intelligence
Classifier: Topic :: Software Development :: Libraries :: Python Modules
Classifier: Topic :: Text Processing :: Linguistic
Classifier: Topic :: Scientific/Engineering :: Information Analysis
Requires-Python: >=3.8
License-File: LICENSE
Requires-Dist: openai>=1.0.0
Requires-Dist: langchain>=0.0.200
Requires-Dist: tiktoken>=0.4.0
Requires-Dist: python-dotenv>=1.0.0
Requires-Dist: pydantic>=2.0.0
Requires-Dist: tqdm>=4.65.0
Requires-Dist: numpy<2.0.0,>=1.21.0
Requires-Dist: pandas<3.0.0,>=1.5.0
Requires-Dist: aiohttp>=3.8.0
Requires-Dist: cachetools>=5.0.0
Requires-Dist: tenacity>=8.0.0
Requires-Dist: nltk>=3.8.1
Requires-Dist: langdetect>=1.0.9
Provides-Extra: dev
Requires-Dist: pytest>=7.0.0; extra == "dev"
Requires-Dist: pytest-cov>=4.0.0; extra == "dev"
Requires-Dist: black>=23.0.0; extra == "dev"
Requires-Dist: isort>=5.12.0; extra == "dev"
Requires-Dist: flake8>=6.0.0; extra == "dev"
Requires-Dist: mypy>=1.0.0; extra == "dev"
Provides-Extra: all
Requires-Dist: openai>=1.0.0; extra == "all"
Requires-Dist: langchain>=0.0.200; extra == "all"
Requires-Dist: dashscope>=1.0.0; extra == "all"
Requires-Dist: erniebot>=0.1.0; extra == "all"
Dynamic: license-file
